MANIFEST.in
README.txt
setup.py
myPackage/__init__.py
myPackage/somePython.py
myPackage/packageData/sampleData.dat
python_package_example_Johnny_dpp.egg-info/PKG-INFO
python_package_example_Johnny_dpp.egg-info/SOURCES.txt
python_package_example_Johnny_dpp.egg-info/dependency_links.txt
python_package_example_Johnny_dpp.egg-info/requires.txt
python_package_example_Johnny_dpp.egg-info/top_level.txt