Metadata-Version: 1.0
Name: python-package-example-Johnny-dpp
Version: 0.6
Summary: An example python package
Home-page: https://github.com/Johnny205/simplePythonLibrary
Author: Mariusz Grabarczyk
Author-email: grabmar97@gmaiil.com
License: MIT
Platform: UNKNOWN
